cctimesheet/__init__.py
cctimesheet/cli.py
cctimesheet/generator.py
cctimesheet/parser.py
cctimesheet-1.0.1.dist-info/METADATA
cctimesheet-1.0.1.dist-info/WHEEL
cctimesheet-1.0.1.dist-info/entry_points.txt
cctimesheet-1.0.1.dist-info/top_level.txt
cctimesheet-1.0.1.dist-info/RECORD
