Metadata-Version: 2.4
Name: cctimesheet
Version: 1.0.1
Summary: Generate professional timesheets from Claude Code session history
Author: pdenya
License: MIT
Project-URL: Homepage, https://github.com/pdenya/cctimesheet
Project-URL: Repository, https://github.com/pdenya/cctimesheet
Project-URL: Issues, https://github.com/pdenya/cctimesheet/issues
Keywords: claude,timesheet,time-tracking,billing
Classifier: Development Status :: 4 - Beta
Classifier: Intended Audience :: Developers
Classifier: License :: OSI Approved :: MIT License
Classifier: Programming Language :: Python :: 3
Classifier: Programming Language :: Python :: 3.8
Classifier: Programming Language :: Python :: 3.9
Classifier: Programming Language :: Python :: 3.10
Classifier: Programming Language :: Python :: 3.11
Classifier: Programming Language :: Python :: 3.12
Classifier: Topic :: Software Development :: Libraries :: Python Modules
Classifier: Topic :: Office/Business
Requires-Python: >=3.8
